autoplaywright/__init__.py
autoplaywright/prompt.py
autoplaywright/types.py
autoplaywright/async_api/__init__.py
autoplaywright/async_api/deepseek_client.py
autoplaywright/async_api/openai_client.py
autoplaywright/sync_api/__init__.py
autoplaywright/sync_api/deepseek_client.py
autoplaywright/sync_api/openai_client.py
autoplaywright_python-1.0.3.dist-info/METADATA
autoplaywright_python-1.0.3.dist-info/WHEEL
autoplaywright_python-1.0.3.dist-info/top_level.txt
autoplaywright_python-1.0.3.dist-info/RECORD
