Metadata-Version: 2.4
Name: autoplaywright-python
Version: 1.0.3
Summary: Automating Playwright steps using ChatGPT(OpenAI) or DeepSeek in Python
Home-page: https://github.com/Nohet/autoplaywright-python
Author: Nohet
Author-email: igorczupryniak503@gmail.com
License: MIT
Keywords: playwright automation,autoplaywright,playwright ai,playwright with ai,ChatGPT playwright
Classifier: Development Status :: 5 - Production/Stable
Classifier: Intended Audience :: Developers
Classifier: License :: OSI Approved :: MIT License
Classifier: Programming Language :: Python :: 3
Requires-Dist: pydantic
Requires-Dist: openai
Requires-Dist: bs4
Dynamic: author
Dynamic: author-email
Dynamic: classifier
Dynamic: description
Dynamic: description-content-type
Dynamic: home-page
Dynamic: keywords
Dynamic: license
Dynamic: requires-dist
Dynamic: summary
